CoDi.py
__init__.py
contrastive.py
contrastive_augmentation.py
preprocessing.py
codi_bg-0.1.3.dist-info/METADATA
codi_bg-0.1.3.dist-info/WHEEL
codi_bg-0.1.3.dist-info/entry_points.txt
codi_bg-0.1.3.dist-info/top_level.txt
codi_bg-0.1.3.dist-info/RECORD
