Metadata-Version: 2.1
Name: codi_bg
Version: 0.1.3
Summary: CoDi - Contrastive Distance reference-based cell type annotation for spatial transcriptomics.
Home-page: https://github.com/stomics/codi
Author: Vladimir Kovacevic
Author-email: vladimirkovacevic@genomics.cn
License: MIT
Classifier: Programming Language :: Python :: 3
Classifier: License :: OSI Approved :: MIT License
Classifier: Operating System :: OS Independent
Requires-Python: >=3.8
Requires-Dist: matplotlib==3.8.0
Requires-Dist: numpy==1.25.2
Requires-Dist: anndata==0.9.2
Requires-Dist: pandas==2.1.1
Requires-Dist: scanpy==1.9.5
Requires-Dist: torch==2.0.1
Requires-Dist: memory-profiler==0.61.0
Requires-Dist: scikit-learn==1.3.1
